async_image_extractor/__init__.py
async_image_extractor/extractor.py
async_image_extractor-1.1.0.dist-info/licenses/LICENSE
async_image_extractor-1.1.0.dist-info/METADATA
async_image_extractor-1.1.0.dist-info/WHEEL
async_image_extractor-1.1.0.dist-info/top_level.txt
async_image_extractor-1.1.0.dist-info/RECORD
