Metadata-Version: 2.4
Name: async-image-extractor
Version: 1.1.0
Summary: Async Gemini-based image text extractor
Requires-Python: >=3.7
License-File: LICENSE
Requires-Dist: tqdm
Requires-Dist: nest_asyncio
Requires-Dist: pandas
Requires-Dist: google-genai
Requires-Dist: openai
Dynamic: description
Dynamic: description-content-type
Dynamic: license-file
Dynamic: requires-dist
Dynamic: requires-python
Dynamic: summary
